inspect_swe/__init__.py
inspect_swe/_registry.py
inspect_swe/_version.py
inspect_swe/py.typed
inspect_swe/_claude_code/__init__.py
inspect_swe/_claude_code/agentbinary.py
inspect_swe/_claude_code/claude_code.py
inspect_swe/_codex_cli/__init__.py
inspect_swe/_codex_cli/agentbinary.py
inspect_swe/_codex_cli/codex_cli.py
inspect_swe/_tools/__init__.py
inspect_swe/_tools/download.py
inspect_swe/_util/__init__.py
inspect_swe/_util/_async.py
inspect_swe/_util/_yaml.py
inspect_swe/_util/agentbinary.py
inspect_swe/_util/appdirs.py
inspect_swe/_util/centaur.py
inspect_swe/_util/checksum.py
inspect_swe/_util/constants.py
inspect_swe/_util/download.py
inspect_swe/_util/messages.py
inspect_swe/_util/path.py
inspect_swe/_util/platform.py
inspect_swe/_util/sandbox.py
inspect_swe/_util/tarball.py
inspect_swe/_util/toml.py
inspect_swe/_util/trace.py
inspect_swe-0.2.32.dist-info/METADATA
inspect_swe-0.2.32.dist-info/WHEEL
inspect_swe-0.2.32.dist-info/entry_points.txt
inspect_swe-0.2.32.dist-info/licenses/LICENSE
inspect_swe-0.2.32.dist-info/RECORD
