Metadata-Version: 2.4
Name: inspect_swe
Version: 0.2.32
Summary: Software engineering agents for Inspect AI.
Project-URL: Documentation, https://meridianlabs-ai.github.io/inspect_swe/
Project-URL: Source Code, https://github.com/meridianlabs-ai/inspect_swe
Project-URL: Issue Tracker, https://github.com/meridianlabs-ai/inspect_swe/issues
Author: Meridian Labs
License: MIT License
License-File: LICENSE
Requires-Python: >=3.10
Requires-Dist: anyio
Requires-Dist: httpx
Requires-Dist: inspect-ai>=0.3.159
Requires-Dist: nest-asyncio
Requires-Dist: platformdirs
Requires-Dist: pydantic>=2.11.4
Requires-Dist: pyyaml
Requires-Dist: sniffio
Requires-Dist: typing-extensions>=4.9.0
Provides-Extra: dev
Requires-Dist: anthropic; extra == 'dev'
Requires-Dist: ipython; extra == 'dev'
Requires-Dist: mypy; extra == 'dev'
Requires-Dist: openai; extra == 'dev'
Requires-Dist: pytest; extra == 'dev'
Requires-Dist: pytest-dotenv; extra == 'dev'
Requires-Dist: ruff; extra == 'dev'
Requires-Dist: types-pyyaml; extra == 'dev'
Provides-Extra: doc
Requires-Dist: quarto-cli==1.7.31; extra == 'doc'
